tuic_tunnel/__init__.py
tuic_tunnel/tuic.py
tuic_tunnel/bin/darwin/tuic-client-arm64
tuic_tunnel/bin/darwin/tuic-client-x86_64
tuic_tunnel/bin/linux/tuic-client-aarch64
tuic_tunnel/bin/linux/tuic-client-x86_64
tuic_tunnel/bin/win32/tuic-client-amd64.exe
tuic_tunnel-0.1.6.dist-info/LICENSE
tuic_tunnel-0.1.6.dist-info/METADATA
tuic_tunnel-0.1.6.dist-info/WHEEL
tuic_tunnel-0.1.6.dist-info/top_level.txt
tuic_tunnel-0.1.6.dist-info/RECORD
