Metadata-Version: 2.1
Name: tuic-tunnel
Version: 0.1.6
Summary: TUIC tunnel plugin for turbo-tunnel.
Home-page: https://github.com/turbo-tunnel/tuic-tunnel
Author: drunkdream
Author-email: drunkdream@qq.com
License: MIT
Classifier: Development Status :: 3 - Alpha
Classifier: License :: OSI Approved :: MIT License
Classifier: Programming Language :: Python
Classifier: Programming Language :: Python :: 3
Classifier: Programming Language :: Python :: 3.5
Classifier: Programming Language :: Python :: 3.6
Classifier: Programming Language :: Python :: 3.7
Classifier: Programming Language :: Python :: 3.8
Classifier: Programming Language :: Python :: 3.9
Classifier: Programming Language :: Python :: 3.10
Classifier: Intended Audience :: Developers
Requires-Python: >=3.5
License-File: LICENSE
Requires-Dist: turbo-tunnel >=0.17.1
